main.py
script_sender.py
stats.py
tello.py
Controller/__init__.py
Tello_Controller-0.2.dist-info/LICENSE
Tello_Controller-0.2.dist-info/METADATA
Tello_Controller-0.2.dist-info/WHEEL
Tello_Controller-0.2.dist-info/top_level.txt
Tello_Controller-0.2.dist-info/RECORD
