Metadata-Version: 2.1
Name: Tello-Controller
Version: 0.2
Summary: Simple library for using DJI Tello drones
Author-email: Alberto <rossani.alberto4@gmail.com>, botasu06 <botasu06@gmail.com>, Jen1s <lorenzo.uduvidane@itiszuccante.edu.it>
License: MIT License
Project-URL: Homepage, https://github.com/Jen1sS/Tellp/tree/release
Keywords: drone,tello,DJI
Classifier: License :: OSI Approved :: MIT License
Classifier: Programming Language :: Python
Classifier: Programming Language :: Python :: 3
Requires-Python: >=3.8
License-File: LICENSE
